{
  "$schema": "../gen/schemas/desktop-schema.json",
  "identifier": "default",
  "description": "enables the default permissions",
  "windows": [
    "main"
  ],
  "permissions": [
    "core:default",
    "core:window:allow-close",
    "core:window:allow-center",
    "core:window:allow-minimize",
    "core:window:allow-set-focus",
    "core:window:allow-start-dragging",
    "decorum:allow-show-snap-overlay",
    "shell:default",
    "shell:allow-execute",
    "sing-box:default",
    "system-proxy:default",
    "port-plz:default",
    "store:default",
    {
      "identifier": "http:default",
      "allow": [{ "url": "https://*" }]
    }
  ]
}